clock/__init__.py
clock/__main__.py
clock/main.py
clock/utils.py
clock/commands/__init__.py
clock/commands/command_in.py
clock/local_db/LocalDatabase.py
clock/local_db/__init__.py
cloxz-0.7.0.dist-info/METADATA
cloxz-0.7.0.dist-info/WHEEL
cloxz-0.7.0.dist-info/entry_points.txt
cloxz-0.7.0.dist-info/top_level.txt
cloxz-0.7.0.dist-info/RECORD
