Metadata-Version: 2.4
Name: cloxz
Version: 0.7.0
Requires-Dist: typer
Requires-Dist: rich
Dynamic: description
Dynamic: description-content-type
Dynamic: requires-dist
